{"help": "Return the metadata of a dataset (package) and its resources.\n\n    :param id: the id or name of the dataset\n    :type id: string\n\n    :rtype: dictionary\n\n    ", "success": true, "result": {"relationships_as_subject": [], "title": "UDP - GDP per capita by metro regions, 2000 - 2060 (JRC LUISA Trend Scenario 2016)", "type_of_dataset": [], "state": "active", "id": "8dcf691b-48ea-48d0-9673-ff9254811101", "geographical_coverage": ["http://publications.europa.eu/resource/authority/country/GBR", "http://publications.europa.eu/resource/authority/country/HUN", "http://publications.europa.eu/resource/authority/country/LTU", "http://publications.europa.eu/resource/authority/country/BGR", "http://publications.europa.eu/resource/authority/country/CZE", "http://publications.europa.eu/resource/authority/country/ROU", "http://publications.europa.eu/resource/authority/country/SVK", "http://publications.europa.eu/resource/authority/country/PRT", "http://publications.europa.eu/resource/authority/country/IRL", "http://publications.europa.eu/resource/authority/country/HRV", "http://publications.europa.eu/resource/authority/country/SVN", "http://publications.europa.eu/resource/authority/country/NLD", "http://publications.europa.eu/resource/authority/country/GRC", "http://publications.europa.eu/resource/authority/country/AUT", "http://publications.europa.eu/resource/authority/country/FIN", "http://publications.europa.eu/resource/authority/country/DNK", "http://publications.europa.eu/resource/authority/country/CYP", "http://publications.europa.eu/resource/authority/country/EST", "http://publications.europa.eu/resource/authority/country/LUX", "http://publications.europa.eu/resource/authority/country/BEL", "http://publications.europa.eu/resource/authority/country/MLT", "http://publications.europa.eu/resource/authority/country/SWE", "http://publications.europa.eu/resource/authority/country/LVA", "http://publications.europa.eu/resource/authority/country/DEU", "http://publications.europa.eu/resource/authority/country/ITA", "http://publications.europa.eu/resource/authority/country/ESP", "http://publications.europa.eu/resource/authority/country/POL", "http://publications.europa.eu/resource/authority/country/FRA"], "license_id": "http://data.europa.eu/euodp/kos/licence/EuropeanCommission", "interoperability_level": [], "maintainer": null, "groups": [{"title": "http://eurovoc.europa.eu/100146", "display_name": "http://eurovoc.europa.eu/100146", "description": "", "type": "eurovoc_domain", "id": "9cfab07a-710c-4c8f-8810-1a45fe188e86", "name": "eurovoc_domain_100146", "image_display_url": ""}, {"title": "http://eurovoc.europa.eu/100149", "display_name": "http://eurovoc.europa.eu/100149", "description": "", "type": "eurovoc_domain", "id": "64575af8-d310-426a-835d-f0f9b218d16a", "name": "eurovoc_domain_100149", "image_display_url": ""}], "contact_webpage": "http://ec.europa.eu/jrc/", "concepts_eurovoc": [], "author_email": null, "revision_id": "2ad0c629-b3be-4eb9-a9fe-aff608353791", "private": false, "version": null, "isopen": true, "relationships_as_object": [], "organization": {"title": "Joint Research Centre", "type": "organization", "approval_status": "approved", "description": "", "revision_id": "28b63966-20b9-4bc9-826a-7fad675c212f", "image_url": "", "revision_timestamp": "2012-12-12T12:50:55.419747", "is_organization": true, "id": "f54d2193-d1b8-44f3-b31d-33d4d2f998b5", "created": "2012-12-12T13:50:55.444363", "state": "active", "name": "jrc"}, "creator_user_id": "75d0190a-2f12-40ed-a863-b5bf30990d14", "temporal_granularity": [], "language": ["http://publications.europa.eu/resource/authority/language/ENG"], "resources": [{"state": "active", "cache_url": null, "id": "0be636c4-5e2e-4cb2-8da2-1618b0dbc54d", "url": "https://ec.europa.eu/jrc/en/luisa", "url_type": null, "format": "text/html", "created": "2018-05-03T16:52:22.881553", "revision_timestamp": "2018-05-03T14:52:22.446842", "tracking_summary": {"recent": 0, "total": 0}, "resource_type": "http://data.europa.eu/euodp/kos/documentation-type/RelatedDocumentation", "download_total_resource": 2, "revision_id": "2ad0c629-b3be-4eb9-a9fe-aff608353791", "mimetype": null, "description": "The LUISA Territorial Modelling Platform is primarily used for the ex-ante evaluation of EC policies that have a direct or indirect territorial impact", "resource_group_id": "59be11da-c91e-491a-8499-418eb82636d5", "datastore_active": false, "mimetype_inner": null, "position": 2, "hash": "", "name": "LUISA Territorial Modelling Platform", "webstore_url": null, "size": null}, {"state": "active", "cache_url": null, "id": "5e0b20d1-d565-4913-8451-98a059a2cd66", "url": "https://ec.europa.eu/jrc/en/territorial-policies", "url_type": null, "format": "text/html", "created": "2018-05-03T16:52:22.881486", "revision_timestamp": "2018-05-03T14:52:22.446842", "tracking_summary": {"recent": 0, "total": 0}, "resource_type": "http://data.europa.eu/euodp/kos/documentation-type/MainDocumentation", "download_total_resource": 1, "revision_id": "2ad0c629-b3be-4eb9-a9fe-aff608353791", "mimetype": null, "description": "", "resource_group_id": "59be11da-c91e-491a-8499-418eb82636d5", "datastore_active": false, "mimetype_inner": null, "position": 1, "hash": "", "name": "Landing page", "webstore_url": null, "size": null}, {"state": "active", "cache_url": null, "id": "a5e691de-8476-4b8e-9848-f20c14bfbced", "url": "https://doi.org/10.2788/458769", "url_type": null, "format": "", "created": "2018-05-03T16:52:22.881433", "revision_timestamp": "2018-05-03T14:52:22.446842", "tracking_summary": {"recent": 0, "total": 0}, "resource_type": "http://data.europa.eu/euodp/kos/documentation-type/RelatedDocumentation", "download_total_resource": 1, "revision_id": "2ad0c629-b3be-4eb9-a9fe-aff608353791", "mimetype": null, "description": "Batista E Silva F; Dijkstra L; Vizcaino M; Lavalle C. Regionalization of demographic and economic projections: Trend and convergence scenarios from 2015 to 2060. EUR 27924. Luxembourg (Luxembourg): Publications Office of the European Union; 2016. JRC101386", "resource_group_id": "59be11da-c91e-491a-8499-418eb82636d5", "datastore_active": false, "mimetype_inner": null, "position": 0, "hash": "", "name": "Regionalization of demographic and economic projections: Trend and convergence scenarios from 2015 to 2060", "webstore_url": null, "size": null}, {"state": "active", "cache_url": null, "id": "0cfcbb7e-6983-4657-9967-9b72471735d0", "url": "https://cidportal.jrc.ec.europa.eu/ftp/jrc-opendata/LUISA/SecondaryOutput_Indicators/Danube/REF-2016/UDP/GDPCAPTREND/", "url_type": null, "format": "text/csv", "created": "2018-05-03T16:52:22.881696", "revision_timestamp": "2018-05-03T14:52:22.446842", "tracking_summary": {"recent": 0, "total": 0}, "resource_type": "http://www.w3.org/ns/dcat#Download", "download_total_resource": 10, "revision_id": "2ad0c629-b3be-4eb9-a9fe-aff608353791", "mimetype": null, "description": "The compressed zip file contains the information at metro and non-metro regions and country levels from 01-01-2000 to 01-01-2060 in European Union. The data is stored in text/csv format.", "resource_group_id": "59be11da-c91e-491a-8499-418eb82636d5", "datastore_active": false, "mimetype_inner": null, "position": 5, "hash": "", "name": "UDP - GDP per capita by metro regions (Danube)", "webstore_url": null, "size": null}, {"state": "active", "cache_url": null, "id": "25ff5c74-23ab-4486-9965-6b388d7f9467", "url": "https://cidportal.jrc.ec.europa.eu/ftp/jrc-opendata/LUISA/SecondaryOutput_Indicators/Europe/REF-2016/UDP/GDPCAPTREND/", "url_type": null, "format": "text/csv", "created": "2018-05-03T16:52:22.881668", "revision_timestamp": "2018-05-03T14:52:22.446842", "tracking_summary": {"recent": 0, "total": 0}, "resource_type": "http://www.w3.org/ns/dcat#Download", "download_total_resource": 6, "revision_id": "2ad0c629-b3be-4eb9-a9fe-aff608353791", "mimetype": null, "description": "The compressed zip file contains the information at metro and non-metro regions and country levels from 01-01-2000 to 01-01-2060 in European Union. The data is stored in text/csv format.", "resource_group_id": "59be11da-c91e-491a-8499-418eb82636d5", "datastore_active": false, "mimetype_inner": null, "position": 4, "hash": "", "name": "UDP - GDP per capita by metro regions (Europe)", "webstore_url": null, "size": null}, {"state": "active", "cache_url": null, "id": "90a99a88-dac4-4827-9456-173fe574eaca", "url": "http://urban.jrc.ec.europa.eu", "url_type": null, "format": "text/html", "created": "2018-05-03T16:52:22.881597", "revision_timestamp": "2018-05-03T14:52:22.446842", "tracking_summary": {"recent": 0, "total": 0}, "resource_type": "http://data.europa.eu/euodp/kos/documentation-type/RelatedDocumentation", "download_total_resource": 2, "revision_id": "2ad0c629-b3be-4eb9-a9fe-aff608353791", "mimetype": null, "description": "The Urban Data Platform is a joint initiative of the Directorate General Joint Research Centre (DG JRC) and the Directorate General for Regional and Urban Policy (DG REGIO) of the European Commission. It provides an access point to exchange information on the status and trends of European cities and regions.It visualizes data via maps at three different geographical units including EU-wide Cities/Greater Cities, Functional Urban Areas and Metropolitan Regions. It also includes time series graphs for selected cities, for Metropolitan Regions, and by degree of urbanisation.", "resource_group_id": "59be11da-c91e-491a-8499-418eb82636d5", "datastore_active": false, "mimetype_inner": null, "position": 3, "hash": "", "name": "Urban Data Platform", "webstore_url": null, "size": null}], "type": "dataset", "maintainer_email": null, "status": ["http://data.europa.eu/euodp/kos/dataset-status/Completed"], "rdf": "<rdf:RDF xmlns:dcat=\"http://www.w3.org/ns/dcat#\" xmlns:dcterms=\"http://purl.org/dc/terms/\" xmlns:ecodp=\"http://data.europa.eu/euodp/ontologies/ec-odp#\" xmlns:foaf=\"http://xmlns.com/foaf/0.1/\" xmlns:rdf=\"http://www.w3.org/1999/02/22-rdf-syntax-ns#\" xmlns:skos=\"http://www.w3.org/2004/02/skos/core#\">\n  <dcat:Dataset rdf:about=\"http://data.europa.eu/89h/jrc-luisa-udp-gdpcaptrend-trend-2016\">\n    <ecodp:ckan-name>jrc-luisa-udp-gdpcaptrend-trend-2016</ecodp:ckan-name>\n    <ecodp:contactPoint>\n      <foaf:Agent>\n        <foaf:mbox>carlo.lavalle@ec.europa.eu</foaf:mbox>\n        <foaf:name>European Commission, Joint Research Centre (JRC)</foaf:name>\n        <foaf:workplaceHomepage>http://ec.europa.eu/jrc/</foaf:workplaceHomepage>\n      </foaf:Agent>\n    </ecodp:contactPoint>\n    <ecodp:datasetStatus>\n      <skos:Concept rdf:about=\"http://data.europa.eu/euodp/kos/dataset-status/Completed\"/>\n    </ecodp:datasetStatus>\n    <ecodp:isDocumentedBy>\n      <rdf:Description rdf:about=\"https://doi.org/10.2788/458769\">\n        <ecodp:accessURL rdf:datatype=\"http://www.w3.org/2001/XMLSchema#anyURI\">https://doi.org/10.2788/458769</ecodp:accessURL>\n        <ecodp:documentationType rdf:resource=\"http://data.europa.eu/euodp/kos/documentation-type/RelatedDocumentation\"/>\n        <dcterms:description>Batista E Silva F; Dijkstra L; Vizcaino M; Lavalle C. Regionalization of demographic and economic projections: Trend and convergence scenarios from 2015 to 2060. EUR 27924. Luxembourg (Luxembourg): Publications Office of the European Union; 2016. JRC101386</dcterms:description>\n        <dcterms:title xml:lang=\"en\">Regionalization of demographic and economic projections: Trend and convergence scenarios from 2015 to 2060</dcterms:title>\n      </rdf:Description>\n    </ecodp:isDocumentedBy>\n    <ecodp:isDocumentedBy>\n      <rdf:Description rdf:about=\"https://ec.europa.eu/jrc/en/territorial-policies\">\n        <ecodp:accessURL rdf:datatype=\"http://www.w3.org/2001/XMLSchema#anyURI\">https://ec.europa.eu/jrc/en/territorial-policies</ecodp:accessURL>\n        <ecodp:documentationFormat>text/html</ecodp:documentationFormat>\n        <ecodp:documentationType rdf:resource=\"http://data.europa.eu/euodp/kos/documentation-type/MainDocumentation\"/>\n        <dcterms:title xml:lang=\"en\">Landing page</dcterms:title>\n      </rdf:Description>\n    </ecodp:isDocumentedBy>\n    <ecodp:isDocumentedBy>\n      <rdf:Description>\n        <ecodp:accessURL rdf:datatype=\"http://www.w3.org/2001/XMLSchema#anyURI\">https://ec.europa.eu/jrc/en/luisa</ecodp:accessURL>\n        <ecodp:documentationFormat>text/html</ecodp:documentationFormat>\n        <ecodp:documentationType rdf:resource=\"http://data.europa.eu/euodp/kos/documentation-type/RelatedDocumentation\"/>\n        <dcterms:description xml:lang=\"en\">The LUISA Territorial Modelling Platform is primarily used for the ex-ante evaluation of EC policies that have a direct or indirect territorial impact</dcterms:description>\n        <dcterms:title xml:lang=\"en\">LUISA Territorial Modelling Platform</dcterms:title>\n      </rdf:Description>\n    </ecodp:isDocumentedBy>\n    <ecodp:isDocumentedBy>\n      <rdf:Description>\n        <ecodp:accessURL rdf:datatype=\"http://www.w3.org/2001/XMLSchema#anyURI\">http://urban.jrc.ec.europa.eu</ecodp:accessURL>\n        <ecodp:documentationFormat>text/html</ecodp:documentationFormat>\n        <ecodp:documentationType rdf:resource=\"http://data.europa.eu/euodp/kos/documentation-type/RelatedDocumentation\"/>\n        <dcterms:description xml:lang=\"en\">The Urban Data Platform is a joint initiative of the Directorate General Joint Research Centre (DG JRC) and the Directorate General for Regional and Urban Policy (DG REGIO) of the European Commission. It provides an access point to exchange information on the status and trends of European cities and regions.It visualizes data via maps at three different geographical units including EU-wide Cities/Greater Cities, Functional Urban Areas and Metropolitan Regions. It also includes time series graphs for selected cities, for Metropolitan Regions, and by degree of urbanisation.</dcterms:description>\n        <dcterms:title xml:lang=\"en\">Urban Data Platform</dcterms:title>\n      </rdf:Description>\n    </ecodp:isDocumentedBy>\n    <ecodp:keyword xml:lang=\"en\">Economy and finance</ecodp:keyword>\n    <ecodp:keyword xml:lang=\"en\">Health</ecodp:keyword>\n    <ecodp:keyword xml:lang=\"en\">Population and society</ecodp:keyword>\n    <dcterms:description xml:lang=\"en\">Historical (observations) data and projections (modelled) of total GDP per capita in purchasing power parities (PPS) per metro region (unit:Thousand Euros). Historical regional data of GDP per capita were calculated from the completed historical series of values of GDP in pps and population with data taken from EUROSTAT's online database. Projection data of GDP in PPS and population were calculated assuming a trend scenario where past regional growth rates for each parameter converge linearly to national growth rates in 2035, and from 2035 onwards, each parameter grows at the same pace in all regions within each country. Projected values of GDP and population respect country totals from the reference projections of DG ECFIN (GDP) and EUROSTAT (population).</dcterms:description>\n    <dcterms:identifier>jrc-luisa-udp-gdpcaptrend-trend-2016</dcterms:identifier>\n    <dcterms:issued rdf:datatype=\"http://www.w3.org/2001/XMLSchema#date\">2016-11-01</dcterms:issued>\n    <dcterms:language>\n      <skos:Concept rdf:about=\"http://publications.europa.eu/resource/authority/language/ENG\"/>\n    </dcterms:language>\n    <dcterms:license>\n      <skos:Concept rdf:about=\"http://data.europa.eu/euodp/kos/licence/EuropeanCommission\"/>\n    </dcterms:license>\n    <dcterms:modified rdf:datatype=\"http://www.w3.org/2001/XMLSchema#date\">2016-12-01</dcterms:modified>\n    <dcterms:publisher rdf:resource=\"http://publications.europa.eu/resource/authority/corporate-body/JRC\"/>\n    <dcterms:spatial>\n      <skos:Concept rdf:about=\"http://publications.europa.eu/resource/authority/country/AUT\"/>\n    </dcterms:spatial>\n    <dcterms:spatial>\n      <skos:Concept rdf:about=\"http://publications.europa.eu/resource/authority/country/BEL\"/>\n    </dcterms:spatial>\n    <dcterms:spatial>\n      <skos:Concept rdf:about=\"http://publications.europa.eu/resource/authority/country/BGR\"/>\n    </dcterms:spatial>\n    <dcterms:spatial>\n      <skos:Concept rdf:about=\"http://publications.europa.eu/resource/authority/country/CYP\"/>\n    </dcterms:spatial>\n    <dcterms:spatial>\n      <skos:Concept rdf:about=\"http://publications.europa.eu/resource/authority/country/CZE\"/>\n    </dcterms:spatial>\n    <dcterms:spatial>\n      <skos:Concept rdf:about=\"http://publications.europa.eu/resource/authority/country/DEU\"/>\n    </dcterms:spatial>\n    <dcterms:spatial>\n      <skos:Concept rdf:about=\"http://publications.europa.eu/resource/authority/country/DNK\"/>\n    </dcterms:spatial>\n    <dcterms:spatial>\n      <skos:Concept rdf:about=\"http://publications.europa.eu/resource/authority/country/ESP\"/>\n    </dcterms:spatial>\n    <dcterms:spatial>\n      <skos:Concept rdf:about=\"http://publications.europa.eu/resource/authority/country/EST\"/>\n    </dcterms:spatial>\n    <dcterms:spatial>\n      <skos:Concept rdf:about=\"http://publications.europa.eu/resource/authority/country/FIN\"/>\n    </dcterms:spatial>\n    <dcterms:spatial>\n      <skos:Concept rdf:about=\"http://publications.europa.eu/resource/authority/country/FRA\"/>\n    </dcterms:spatial>\n    <dcterms:spatial>\n      <skos:Concept rdf:about=\"http://publications.europa.eu/resource/authority/country/GBR\"/>\n    </dcterms:spatial>\n    <dcterms:spatial>\n      <skos:Concept rdf:about=\"http://publications.europa.eu/resource/authority/country/GRC\"/>\n    </dcterms:spatial>\n    <dcterms:spatial>\n      <skos:Concept rdf:about=\"http://publications.europa.eu/resource/authority/country/HRV\"/>\n    </dcterms:spatial>\n    <dcterms:spatial>\n      <skos:Concept rdf:about=\"http://publications.europa.eu/resource/authority/country/HUN\"/>\n    </dcterms:spatial>\n    <dcterms:spatial>\n      <skos:Concept rdf:about=\"http://publications.europa.eu/resource/authority/country/IRL\"/>\n    </dcterms:spatial>\n    <dcterms:spatial>\n      <skos:Concept rdf:about=\"http://publications.europa.eu/resource/authority/country/ITA\"/>\n    </dcterms:spatial>\n    <dcterms:spatial>\n      <skos:Concept rdf:about=\"http://publications.europa.eu/resource/authority/country/LTU\"/>\n    </dcterms:spatial>\n    <dcterms:spatial>\n      <skos:Concept rdf:about=\"http://publications.europa.eu/resource/authority/country/LUX\"/>\n    </dcterms:spatial>\n    <dcterms:spatial>\n      <skos:Concept rdf:about=\"http://publications.europa.eu/resource/authority/country/LVA\"/>\n    </dcterms:spatial>\n    <dcterms:spatial>\n      <skos:Concept rdf:about=\"http://publications.europa.eu/resource/authority/country/MLT\"/>\n    </dcterms:spatial>\n    <dcterms:spatial>\n      <skos:Concept rdf:about=\"http://publications.europa.eu/resource/authority/country/NLD\"/>\n    </dcterms:spatial>\n    <dcterms:spatial>\n      <skos:Concept rdf:about=\"http://publications.europa.eu/resource/authority/country/POL\"/>\n    </dcterms:spatial>\n    <dcterms:spatial>\n      <skos:Concept rdf:about=\"http://publications.europa.eu/resource/authority/country/PRT\"/>\n    </dcterms:spatial>\n    <dcterms:spatial>\n      <skos:Concept rdf:about=\"http://publications.europa.eu/resource/authority/country/ROU\"/>\n    </dcterms:spatial>\n    <dcterms:spatial>\n      <skos:Concept rdf:about=\"http://publications.europa.eu/resource/authority/country/SVK\"/>\n    </dcterms:spatial>\n    <dcterms:spatial>\n      <skos:Concept rdf:about=\"http://publications.europa.eu/resource/authority/country/SVN\"/>\n    </dcterms:spatial>\n    <dcterms:spatial>\n      <skos:Concept rdf:about=\"http://publications.europa.eu/resource/authority/country/SWE\"/>\n    </dcterms:spatial>\n    <dcterms:subject>\n      <skos:Concept rdf:about=\"http://eurovoc.europa.eu/100146\"/>\n    </dcterms:subject>\n    <dcterms:subject>\n      <skos:Concept rdf:about=\"http://eurovoc.europa.eu/100149\"/>\n    </dcterms:subject>\n    <dcterms:title xml:lang=\"en\">UDP - GDP per capita by metro regions, 2000 - 2060 (JRC LUISA Trend Scenario 2016)</dcterms:title>\n    <dcat:distribution>\n      <dcat:Download>\n        <ecodp:distributionFormat>text/csv</ecodp:distributionFormat>\n        <dcterms:description xml:lang=\"en\">The compressed zip file contains the information at metro and non-metro regions and country levels from 01-01-2000 to 01-01-2060 in European Union. The data is stored in text/csv format.</dcterms:description>\n        <dcterms:title xml:lang=\"en\">UDP - GDP per capita by metro regions (Europe)</dcterms:title>\n        <dcat:accessURL rdf:datatype=\"http://www.w3.org/2001/XMLSchema#anyURI\">https://cidportal.jrc.ec.europa.eu/ftp/jrc-opendata/LUISA/SecondaryOutput_Indicators/Europe/REF-2016/UDP/GDPCAPTREND/</dcat:accessURL>\n      </dcat:Download>\n    </dcat:distribution>\n    <dcat:distribution>\n      <dcat:Download>\n        <ecodp:distributionFormat>text/csv</ecodp:distributionFormat>\n        <dcterms:description xml:lang=\"en\">The compressed zip file contains the information at metro and non-metro regions and country levels from 01-01-2000 to 01-01-2060 in European Union. The data is stored in text/csv format.</dcterms:description>\n        <dcterms:title xml:lang=\"en\">UDP - GDP per capita by metro regions (Danube)</dcterms:title>\n        <dcat:accessURL rdf:datatype=\"http://www.w3.org/2001/XMLSchema#anyURI\">https://cidportal.jrc.ec.europa.eu/ftp/jrc-opendata/LUISA/SecondaryOutput_Indicators/Danube/REF-2016/UDP/GDPCAPTREND/</dcat:accessURL>\n      </dcat:Download>\n    </dcat:distribution>\n  </dcat:Dataset>\n<dcat:Catalog xmlns:foaf=\"http://xmlns.com/foaf/0.1/#\" xmlns:dct=\"http://purl.org/dc/terms/#\" rdf:about=\"http://data.europa.eu/euodp/\"><dcat:record><dcat:CatalogRecord rdf:about=\"http://data.europa.eu/euodp/euodp/data/dataset/jrc-luisa-udp-gdpcaptrend-trend-2016\"><foaf:primaryTopic>http://data.europa.eu/89h/jrc-luisa-udp-gdpcaptrend-trend-2016</foaf:primaryTopic><dct:modified>2018-05-03T16:52:22.420878</dct:modified><dct:issued>2018-05-03T16:52:22.420878</dct:issued></dcat:CatalogRecord></dcat:record></dcat:Catalog></rdf:RDF>", "url": "http://data.europa.eu/89h/jrc-luisa-udp-gdpcaptrend-trend-2016", "contact_email": "carlo.lavalle@ec.europa.eu", "license_title": "Legal Notice", "owner_org": "f54d2193-d1b8-44f3-b31d-33d4d2f998b5", "tracking_summary": {"recent": 1, "total": 1}, "author": null, "metadata_modified": "2018-05-03T14:52:22.599245", "contact_name": "European Commission, Joint Research Centre (JRC)", "description": "Historical (observations) data and projections (modelled) of total GDP per capita in purchasing power parities (PPS) per metro region (unit:Thousand Euros). Historical regional data of GDP per capita were calculated from the completed historical series of values of GDP in pps and population with data taken from EUROSTAT's online database. Projection data of GDP in PPS and population were calculated assuming a trend scenario where past regional growth rates for each parameter converge linearly to national growth rates in 2035, and from 2035 onwards, each parameter grows at the same pace in all regions within each country. Projected values of GDP and population respect country totals from the reference projections of DG ECFIN (GDP) and EUROSTAT (population).", "capacity": null, "keywords": [{"display_name": "Economy and finance", "id": "fa3dd1e0-4a35-4b32-90bd-c5e2f0e76825", "state": "active", "name": "Economy and finance", "vocabulary_id": null, "revision_timestamp": "2018-05-03T14:52:22.446842"}, {"display_name": "Health", "id": "42e9e5e2-f450-4a12-8b25-f60fb87a2256", "state": "active", "name": "Health", "vocabulary_id": null, "revision_timestamp": "2018-05-03T14:52:22.446842"}, {"display_name": "Population and society", "id": "14d94a8c-7acd-4aa5-8dc4-42162e7bf388", "state": "active", "name": "Population and society", "vocabulary_id": null, "revision_timestamp": "2018-05-03T14:52:22.446842"}], "metadata_created": "2018-05-03T14:52:22.446842", "revision_timestamp": "2018-05-03T14:52:22.446842", "num_tags": 33, "modified_date": "2016-12-01", "num_resources": 6, "name": "jrc-luisa-udp-gdpcaptrend-trend-2016", "identifier": "jrc-luisa-udp-gdpcaptrend-trend-2016", "license_url": "http://ec.europa.eu/geninfo/legal_notices_en.htm", "release_date": "2016-11-01"}}